chunky/__init__.py
chunky/chunk.py
chunky/errors.py
chunky/world.py
hamolicious_chunky-1.1.1.dist-info/LICENCE
hamolicious_chunky-1.1.1.dist-info/METADATA
hamolicious_chunky-1.1.1.dist-info/WHEEL
hamolicious_chunky-1.1.1.dist-info/top_level.txt
hamolicious_chunky-1.1.1.dist-info/RECORD
