Metadata-Version: 2.1
Name: hamolicious-chunky
Version: 1.1.1
Summary: A chunking system for game development
Home-page: https://github.com/hamolicious/Chunky
Author: Hamolicous
Author-email: hamolicious@protonmail.com
License: UNKNOWN
Project-URL: Bug Tracker, https://github.com/hamolicious/Chunky/issues
Platform: UNKNOWN
Classifier: Programming Language :: Python :: 3
Classifier: License :: OSI Approved :: MIT License
Classifier: Operating System :: OS Independent
Requires-Python: >=3.6
License-File: LICENCE
